{
  "vid": "46aeba13-64a1-11e1-bc16-0023ae8e59f0",
  "topic": "openx -- undisclosed security issue",
  "affects": [
    {
      "name": [
        "openx"
      ],
      "range": [
        {
          "lt": "2.8.9"
        }
      ]
    }
  ],
  "description": {
    "xmlns": "http://www.w3.org/1999/xhtml",
    "text": "\n\t<p>OpenX does not provide information about vulnerabilities beyond their\n\t  existence.</p>\n      "
  },
  "references": {
    "url": [
      "http://blog.openx.org/12/security-matters-3"
    ]
  },
  "dates": {
    "discovery": "2011-12-01",
    "entry": "2012-03-02",
    "modified": "2012-07-08"
  }
}
