{
	"vid": "515b4327-cf8a-11e5-96d6-14dae9d210b8",
	"topic": "dnscrypt-proxy -- code execution",
	"affects": [
		{
			"name": [
				"dnscrypt-proxy"
			],
			"range": [
				{
					"lt": "1.6.1",
					"ge": "1.1.0"
				}
			]
		}
	],
	"description": {
		"xmlns": "http://www.w3.org/1999/xhtml",
		"text": "\n\t<p>Frank Denis reports:</p>\n\t<blockquote cite=\"https://github.com/jedisct1/dnscrypt-proxy/blob/1d129f7d5f0d469308967cbe4eacb4a6919f1fa1/NEWS#L2-L8\">\n\t  <p>Malformed packets could lead to denial of service or code\n\t    execution.</p>\n\t</blockquote>\n      "
	},
	"references": {
		"url": [
			"https://github.com/jedisct1/dnscrypt-proxy/blob/1d129f7d5f0d469308967cbe4eacb4a6919f1fa1/NEWS#L2-L8"
		]
	},
	"dates": {
		"discovery": "2016-02-02",
		"entry": "2016-02-10",
		"modified": "2016-02-14"
	}
}
