{
  "vid": "9704930c-3bb7-11e7-93f7-d43d7e971a1b",
  "topic": "gitlab -- Various security issues",
  "affects": [
    {
      "name": [
        "gitlab"
      ],
      "range": [
        {
          "ge": "6.6.0",
          "le": "8.17.5"
        },
        {
          "ge": "9.0.0",
          "le": "9.0.6"
        },
        {
          "ge": "9.1.0",
          "le": "9.1.2"
        }
      ]
    }
  ],
  "description": {
    "xmlns": "http://www.w3.org/1999/xhtml",
    "text": "\n\t<p>GitLab reports:</p>\n\t<blockquote cite=\"https://about.gitlab.com/2017/05/08/gitlab-9-dot-1-dot-3-security-release/\">\n\t  <p>Please reference CVE/URL list for details</p>\n\t</blockquote>\n      "
  },
  "references": {
    "url": [
      "https://about.gitlab.com/2017/05/08/gitlab-9-dot-1-dot-3-security-release/"
    ]
  },
  "dates": {
    "discovery": "2017-05-08",
    "entry": "2017-05-18",
    "modified": "2017-05-30"
  }
}
