{
	"vid": "b13414c9-50ba-11e0-975a-000c29cc39d3",
	"topic": "hiawatha -- integer overflow in Content-Length header parsing",
	"affects": [
		{
			"name": [
				"hiawatha"
			],
			"range": [
				{
					"lt": "7.4_1"
				}
			]
		}
	],
	"description": {
		"xmlns": "http://www.w3.org/1999/xhtml",
		"text": "\n\t<p>Hugo Leisink reports:</p>\n\t<blockquote cite=\"http://www.hiawatha-webserver.org/weblog/16\">\n\t  <p>A bug has been found in version 7.4 of the Hiawatha webserver,\n\t    which could lead to a server crash. This is caused by an integer\n\t    overflow in the routine that reads the HTTP request. A too large\n\t    value of the Content-Length HTTP header results in an overflow.</p>\n\t</blockquote>\n      "
	},
	"references": {
		"url": [
			"http://www.hiawatha-webserver.org/weblog/16",
			"http://secunia.com/advisories/43660/",
			"http://securityvulns.com/Zdocument902.html",
			"http://packetstormsecurity.org/files/99021/Hiawatha-WebServer-7.4-Denial-Of-Service.html",
			"http://seclists.org/bugtraq/2011/Mar/65"
		]
	},
	"dates": {
		"discovery": "2011-02-25",
		"entry": "2011-03-17"
	}
}
