{
	"vid": "bcf56a42-9df8-11e8-afb0-589cfc0f81b0",
	"topic": "gitea -- TOTP passcode reuse",
	"affects": [
		{
			"name": [
				"gitea"
			],
			"range": [
				{
					"lt": "1.5.0"
				}
			]
		}
	],
	"description": {
		"xmlns": "http://www.w3.org/1999/xhtml",
		"text": "\n\t<p>The Gitea project reports:</p>\n\t<blockquote cite=\"https://blog.gitea.io/2018/08/gitea-1.5.0-is-released/\">\n\t  <p>TOTP passcodes can be reused.</p>\n\t</blockquote>\n      "
	},
	"references": {
		"url": [
			"https://github.com/go-gitea/gitea/pull/3878"
		]
	},
	"dates": {
		"discovery": "2018-05-01",
		"entry": "2018-08-12"
	}
}
