{
	"vid": "ef3423e4-d056-11e7-a52c-002590263bf5",
	"topic": "codeigniter -- input validation bypass",
	"affects": [
		{
			"name": [
				"codeigniter"
			],
			"range": [
				{
					"lt": "3.1.6"
				}
			]
		}
	],
	"description": {
		"xmlns": "http://www.w3.org/1999/xhtml",
		"text": "\n\t<p>The CodeIgniter changelog reports:</p>\n\t<blockquote cite=\"https://www.codeigniter.com/user_guide/changelog.html\">\n\t  <p>Security: Fixed a potential object injection in Cache Library 'apc'\n\t    driver when save() is used with $raw = TRUE.</p>\n\t</blockquote>\n      "
	},
	"references": {
		"url": [
			"https://www.codeigniter.com/user_guide/changelog.html"
		]
	},
	"dates": {
		"discovery": "2017-09-25",
		"entry": "2017-11-23"
	}
}
